Workbook

Sheet Pre-trip bookings
A1: 2026 Makharia Family Reunion · Expense Tracker
A2: Sheet 1 of 3 — Pre-trip bookings (everything booked before Aug 22). Blue = input, yellow = needs an amount filled in.
A4: Date paid | B4: Category | C4: Description | D4: Paid by | E4: Amount (USD) | F4: Refundable? | G4: Cancel deadline | H4: Confirmation # | I4: Paid to | J4: Who benefits | K4: Notes
A5: 2026-05-12 | B5: Dining | C5: Glorietta — Dadu's 75th private room (Aug 23) | D5: Rohit | E5: 0 | F5: 10-day cancel | G5: 2026-08-13 | H5: phone reservation | I5: Glorietta Trattoria | J5: All 12 | K5: No deposit charged yet; menu finalize ~Aug 9
A6: 2026-05-13 | B6: Activity | C6: Barker-Ewing private float (Aug 24 12:00 PM) | D6: Rohit | E6: 1200 | F6: Full ≥72hr | G6: 2026-08-21 | H6: 8L5Q8N9T7K3V2H7F | I6: Barker-Ewing Scenic Floats | J6: All 12 | K6: Pickup Moose Village. 307-733-1800.
A7: 2026-05-19 | B7: Flight | C7: UA 2472 SFO→JAC · 3 Agarwal inbound (HTXHKY) | D7: Rohit | E7: 0 | F7: Non-refundable | G7: — | H7: HTXHKY | I7: United Airlines | J7: Agarwal (3) | K7: Seats 34D/E/F. Aug 22.
A8: 2026-05-19 | B8: Flight | C8: UA 1702 BZN→SFO · 5 non-refundable (HVFBCM) | D8: Ritesh | E8: 0 | F8: Non-refundable | G8: — | H8: HVFBCM | I8: United Airlines | J8: Detroit-onward(5) | K8: Seats 34A/B/C, 35B/C. Aug 29.
A9: 2026-05-19 | B9: Flight | C9: UA 1702 BZN→SFO · 3 refundable Agarwal (HVZD9X) | D9: Ritesh | E9: 0 | F9: Until departure | G9: 2026-08-29 | H9: HVZD9X | I9: United Airlines | J9: Agarwal (3) | K9: Seats 35D/E/F. Aug 29.
A10: 2026-05-20 | B10: Lodging | C10: Hal'e Teton initial payment (Aug 22-26 Jackson) | D10: Rohit | E10: 5813.36 | F10: 6% forfeit ≤30d | G10: 2026-07-23 | H10: #112575 | I10: Rendezvous Mountain Rentals | J10: All 12 | K10: Trip insurance included. 307-739-9050.
A11: 2026-07-23 | B11: Lodging | C11: Hal'e Teton final payment (due Jul 23) | D11: Rohit | E11: 5813.36 | F11: No refund after | G11: 2026-07-23 | H11: #112575 | I11: Rendezvous Mountain Rentals | J11: All 12 | K11: Auto-charged Jul 23.
A12: 2026-05-20 | B12: Lodging | C12: Yellowstone Luxury Cabin Retreat (Aug 26-29 W. Yellowstone) | D12: Rohit | E12: 6030.9 | F12: 100% by Jul 27 | G12: 2026-07-27 | H12: ORB17812924 | I12: Vrbo property 9746176ha | J12: All 12 | K12: +$1,500 refundable deposit at property on arrival (returned post-stay)
A13: 2026-05-20 | B13: Vehicle | C13: Enterprise Mini Van #1 (Ritesh) · JAC→BZN Aug 22-29 | D13: Ritesh | E13: 0 | F13: Through Aug 20 | G13: 2026-08-20 | H13: C491501172 / 2112908075 | I13: Enterprise via Costco Travel | J13: All 12 | K13: Driver: Ritesh Kumar Makharia. 1-866-328-1385.
A14: 2026-05-20 | B14: Vehicle | C14: Enterprise Mini Van #2 (Parul) · JAC→BZN Aug 22-29 | D14: Ritesh | E14: 0 | F14: Through Aug 20 | G14: 2026-08-20 | H14: C491501176 / 2112908572 | I14: Enterprise via Costco Travel | J14: All 12 | K14: Driver: Parul Ritesh Kumar Makharia.
A15: 2026-?? | B15: Flight | C15: DL 0935 + DL 0417 · 9 Detroit inbound (DTW→SLC→JAC) | D15: Rohit | E15: =9*304.19 -> 2737.71 | F15: Delta main cabin | G15: — | H15: TBD | I15: Delta Airlines | J15: Detroit (9) | K15: Aug 22 · 12:15 PM → 4:57 PM (DTW→SLC→JAC). $304.19/ticket × 9 = total.
A16: 2026-?? | B16: Flight | C16: DL 0364 · 4 Detroit return (BZN→DTW) | D16: Rohit | E16: 0 | F16: TBD | G16: — | H16: TBD | I16: Delta Airlines | J16: Detroit-home (4) | K16: Aug 29 · 3:38 PM → 8:54 PM.
D17: Sheet total | E17: =SUM(E5:E16) -> 21595.33

Sheet During-trip log
A1: During-trip expenses (Aug 22-29)
A2: Add a row for every shared expense — gas, groceries, lunches, tips, etc. Anyone can fill in. Sum auto-tracks below.
A4: Date | B4: Day # | C4: Category | D4: Description | E4: Paid by | F4: Amount (USD) | G4: Receipt kept? | H4: Notes
E35: During-trip total | F35: =SUM(F5:F34) -> 0

Sheet Settlement
A1: Settlement summary
A2: Auto-calculated from the other two sheets. Green = cross-sheet reference. Update Paid-by names if different.
A4: BY PERSON
A5: Person | B5: Pre-trip paid | C5: During-trip paid | D5: Total paid
A6: Rohit | B6: =SUMIF('Pre-trip bookings'!D:D,"Rohit",'Pre-trip bookings'!E:E) -> 21595.33 | C6: =SUMIF('During-trip log'!E:E,"Rohit",'During-trip log'!F:F) -> 0 | D6: =B6+C6 -> 21595.33
A7: Ritesh | B7: =SUMIF('Pre-trip bookings'!D:D,"Ritesh",'Pre-trip bookings'!E:E) -> 0 | C7: =SUMIF('During-trip log'!E:E,"Ritesh",'During-trip log'!F:F) -> 0 | D7: =B7+C7 -> 0
A8: Other | B8: =SUMIF('Pre-trip bookings'!D:D,"Other",'Pre-trip bookings'!E:E) -> 0 | C8: =SUMIF('During-trip log'!E:E,"Other",'During-trip log'!F:F) -> 0 | D8: =B8+C8 -> 0
A9: TRIP TOTAL | B9: =SUM(B6:B8) -> 21595.33 | C9: =SUM(C6:C8) -> 0 | D9: =SUM(D6:D8) -> 21595.33
A11: BY CATEGORY
A12: Category | B12: Pre-trip | C12: During-trip | D12: Total
A13: Lodging | B13: =SUMIF('Pre-trip bookings'!B:B,"Lodging",'Pre-trip bookings'!E:E) -> 17657.62 | C13: =SUMIF('During-trip log'!C:C,"Lodging",'During-trip log'!F:F) -> 0 | D13: =B13+C13 -> 17657.62
A14: Flight | B14: =SUMIF('Pre-trip bookings'!B:B,"Flight",'Pre-trip bookings'!E:E) -> 2737.71 | C14: =SUMIF('During-trip log'!C:C,"Flight",'During-trip log'!F:F) -> 0 | D14: =B14+C14 -> 2737.71
A15: Vehicle | B15: =SUMIF('Pre-trip bookings'!B:B,"Vehicle",'Pre-trip bookings'!E:E) -> 0 | C15: =SUMIF('During-trip log'!C:C,"Vehicle",'During-trip log'!F:F) -> 0 | D15: =B15+C15 -> 0
A16: Activity | B16: =SUMIF('Pre-trip bookings'!B:B,"Activity",'Pre-trip bookings'!E:E) -> 1200 | C16: =SUMIF('During-trip log'!C:C,"Activity",'During-trip log'!F:F) -> 0 | D16: =B16+C16 -> 1200
A17: Dining | B17: =SUMIF('Pre-trip bookings'!B:B,"Dining",'Pre-trip bookings'!E:E) -> 0 | C17: =SUMIF('During-trip log'!C:C,"Dining",'During-trip log'!F:F) -> 0 | D17: =B17+C17 -> 0
A18: Food | B18: =SUMIF('Pre-trip bookings'!B:B,"Food",'Pre-trip bookings'!E:E) -> 0 | C18: =SUMIF('During-trip log'!C:C,"Food",'During-trip log'!F:F) -> 0 | D18: =B18+C18 -> 0
A19: Fuel | B19: =SUMIF('Pre-trip bookings'!B:B,"Fuel",'Pre-trip bookings'!E:E) -> 0 | C19: =SUMIF('During-trip log'!C:C,"Fuel",'During-trip log'!F:F) -> 0 | D19: =B19+C19 -> 0
A20: Other | B20: =SUMIF('Pre-trip bookings'!B:B,"Other",'Pre-trip bookings'!E:E) -> 0 | C20: =SUMIF('During-trip log'!C:C,"Other",'During-trip log'!F:F) -> 0 | D20: =B20+C20 -> 0
A22: WHO OWES WHO (equal split assumption)
A23: Assumption: split everything equally across 12 people. For per-family-specific costs (e.g. Agarwal-only flights), adjust manually.
A25: Total trip cost | B25: =D9 -> 21595.33
A26: Travelers | B26: 12
A27: Equal per-person share | B27: =B25/B26 -> 1799.6108
A29: Person | B29: Paid | C29: Owes (share) | D29: Net (+ = owed back; − = owes more)
A30: Rohit | B30: =D6 -> 21595.33 | C30: =B27*1 -> 1799.6108 | D30: =B30-C30 -> 19795.719
A31: Ritesh | B31: =D7 -> 0 | C31: =B27*1 -> 1799.6108 | D31: =B31-C31 -> -1799.6108
A32: Other | B32: =D8 -> 0 | C32: =B27*10 -> 17996.108 | D32: =B32-C32 -> -17996.108
